huaweicloudsdkdataartsfabricep/__init__.py
huaweicloudsdkdataartsfabricep/v1/__init__.py
huaweicloudsdkdataartsfabricep/v1/dataartsfabricep_async_client.py
huaweicloudsdkdataartsfabricep/v1/dataartsfabricep_client.py
huaweicloudsdkdataartsfabricep/v1/model/__init__.py
huaweicloudsdkdataartsfabricep/v1/model/app_instance_config.py
huaweicloudsdkdataartsfabricep/v1/model/base_demand.py
huaweicloudsdkdataartsfabricep/v1/model/delete_service_instance_request.py
huaweicloudsdkdataartsfabricep/v1/model/delete_service_instance_response.py
huaweicloudsdkdataartsfabricep/v1/model/deploy_service_instance_request.py
huaweicloudsdkdataartsfabricep/v1/model/deploy_service_instance_response.py
huaweicloudsdkdataartsfabricep/v1/model/description.py
huaweicloudsdkdataartsfabricep/v1/model/endpoint_id.py
huaweicloudsdkdataartsfabricep/v1/model/error_code.py
huaweicloudsdkdataartsfabricep/v1/model/error_msg.py
huaweicloudsdkdataartsfabricep/v1/model/instance_id.py
huaweicloudsdkdataartsfabricep/v1/model/list_services_instances_request.py
huaweicloudsdkdataartsfabricep/v1/model/list_services_instances_response.py
huaweicloudsdkdataartsfabricep/v1/model/model_service_instance_config.py
huaweicloudsdkdataartsfabricep/v1/model/pgsql_instance_config.py
huaweicloudsdkdataartsfabricep/v1/model/resource_demand.py
huaweicloudsdkdataartsfabricep/v1/model/resource_id.py
huaweicloudsdkdataartsfabricep/v1/model/service_instance_brief_info.py
huaweicloudsdkdataartsfabricep/v1/model/service_instance_config.py
huaweicloudsdkdataartsfabricep/v1/model/service_instance_id.py
huaweicloudsdkdataartsfabricep/v1/model/service_instance_input.py
huaweicloudsdkdataartsfabricep/v1/model/service_instance_name.py
huaweicloudsdkdataartsfabricep/v1/model/service_type.py
huaweicloudsdkdataartsfabricep/v1/model/show_service_instance_detail_request.py
huaweicloudsdkdataartsfabricep/v1/model/show_service_instance_detail_response.py
huaweicloudsdkdataartsfabricep/v1/model/source_ref.py
huaweicloudsdkdataartsfabricep-3.1.184.dist-info/METADATA
huaweicloudsdkdataartsfabricep-3.1.184.dist-info/WHEEL
huaweicloudsdkdataartsfabricep-3.1.184.dist-info/licenses/LICENSE
huaweicloudsdkdataartsfabricep-3.1.184.dist-info/RECORD
